gitcommit_cli/__init__.py
gitcommit_cli/__main__.py
gitcommit_cli/diff_reader.py
gitcommit_cli/hackclubai.py
gitcommit_cli-2.1.1.dist-info/METADATA
gitcommit_cli-2.1.1.dist-info/WHEEL
gitcommit_cli-2.1.1.dist-info/entry_points.txt
gitcommit_cli-2.1.1.dist-info/top_level.txt
gitcommit_cli-2.1.1.dist-info/RECORD
