Metadata-Version: 2.4
Name: gitcommit-cli
Version: 2.1.1
Summary: From staged changes to perfect commits in one command. AI-powered commit message generation that actually understands your code.
Author-email: Nirvaan <nirvaan@gmail.com>
Requires-Python: >=3.8
Requires-Dist: click>=8.1.7
Requires-Dist: GitPython>=3.1.34
Provides-Extra: treesitter
Requires-Dist: tree_sitter[python]>=0.20.0; extra == "treesitter"
Provides-Extra: all
Requires-Dist: tree_sitter[python]>=0.20.0; extra == "all"
